pdf_miner_parser/__init__.py
pdf_miner_parser/parser.py
pdf_miner_parser-0.0.2.dist-info/LICENSE
pdf_miner_parser-0.0.2.dist-info/METADATA
pdf_miner_parser-0.0.2.dist-info/WHEEL
pdf_miner_parser-0.0.2.dist-info/top_level.txt
pdf_miner_parser-0.0.2.dist-info/RECORD
