Metadata-Version: 2.1
Name: pdf-miner-parser
Version: 0.0.2
Summary: Additional parser functionality for the pdf_miner library.
Author: leitegarcia1
Author-email: leitegarcia1@llnl.gov
License: UNKNOWN
Keywords: python,pdf parser,pdf_miner
Platform: UNKNOWN
Classifier: Development Status :: 1 - Planning
Classifier: Intended Audience :: Developers
Classifier: Programming Language :: Python :: 3
Classifier: Operating System :: Unix
Classifier: Operating System :: MacOS :: MacOS X
Classifier: Operating System :: Microsoft :: Windows
License-File: LICENSE
Requires-Dist: pdfminer.six
Requires-Dist: numpy
Requires-Dist: re
